app/__init__.py
app/__main__.py
app/common.py
app/export/__init__.py
app/export/cli.py
app/setup/__init__.py
app/setup/utils.py
app/txt/__init__.py
app/txt/cli.py
app/txt/deprecated_cli.py
app/xlsx/__init__.py
app/xlsx/main.py
screenapi_cli-0.1.6.dist-info/LICENSE
screenapi_cli-0.1.6.dist-info/METADATA
screenapi_cli-0.1.6.dist-info/WHEEL
screenapi_cli-0.1.6.dist-info/entry_points.txt
screenapi_cli-0.1.6.dist-info/RECORD
