Metadata-Version: 2.1
Name: screenapi-cli
Version: 0.1.6
Summary: A cli interface to interact with screenapi
License: MIT
Author: RONY
Author-email: iamrony777@pm.me
Requires-Python: >=3.10,<4.0
Classifier: License :: OSI Approved :: MIT License
Classifier: Programming Language :: Python :: 3
Classifier: Programming Language :: Python :: 3.10
Classifier: Programming Language :: Python :: 3.11
Classifier: Programming Language :: Python :: 3.12
Requires-Dist: httpx[http2] (>=0.27.0,<0.28.0)
Requires-Dist: openpyxl (>=3.1.2,<4.0.0)
Requires-Dist: pandas (>=2.2.1,<3.0.0)
Requires-Dist: python-calamine (>=0.2.0,<0.3.0)
Requires-Dist: typer[all] (>=0.10.0,<0.11.0)
